hf_ehr/__init__.py
hf_ehr/config.py
hf_ehr/utils.py
hf_ehr/data/datasets.py
hf_ehr/data/tokenization.py
hf_ehr/eval/ehrshot.py
hf_ehr/eval/val_ppl.py
hf_ehr/logger/reloggers.py
hf_ehr/meds_dev/config.py
hf_ehr/meds_dev/generate_labels.py
hf_ehr/models/base.py
hf_ehr/models/based.py
hf_ehr/models/bert.py
hf_ehr/models/gpt.py
hf_ehr/models/hyena.py
hf_ehr/models/llama.py
hf_ehr/models/mamba.py
hf_ehr/models/t5.py
hf_ehr/notebooks/dataset_stats/avg_brier_across_metrics.py
hf_ehr/notebooks/dataset_stats/gen_dataset_stats.py
hf_ehr/notebooks/dataset_stats/metric_quartile_p_value.py
hf_ehr/notebooks/dataset_stats/starr_irregularity_nlp_overlay.py
hf_ehr/notebooks/dataset_stats/train_seq_lengths.py
hf_ehr/notebooks/dataset_stats/utils.py
hf_ehr/notebooks/dataset_stats/utils_new.py
hf_ehr/notebooks/ehr_specific_properties/bucket_by_metrics.py
hf_ehr/notebooks/ehr_specific_properties/calc_stratification_metrics.py
hf_ehr/notebooks/ehr_specific_properties/clmbr_metric_plot.py
hf_ehr/notebooks/ehr_specific_properties/starr_eda.py
hf_ehr/notebooks/ehr_specific_properties/utils.py
hf_ehr/notebooks/ehrshot/ehrshot_att_v_non_att.py
hf_ehr/notebooks/n_gram_stats/nlp_n_gram_counter.py
hf_ehr/notebooks/token_v_ppl/val_ppl_nlp.py
hf_ehr/scripts/run.py
hf_ehr/scripts/carina/main.py
hf_ehr/scripts/datasets/dataset_statistics.py
hf_ehr/scripts/datasets/split_meds_dataset.py
hf_ehr/scripts/eval/inference_time.py
hf_ehr/scripts/huggingface/hf_readme.py
hf_ehr/scripts/huggingface/hf_test.py
hf_ehr/scripts/huggingface/hf_upload.py
hf_ehr/scripts/huggingface/test_checkpoints.py
hf_ehr/scripts/shahlab-secure/main.py
hf_ehr/tokenizers/create_cehr.py
hf_ehr/tokenizers/create_clmbr.py
hf_ehr/tokenizers/create_cookbook.py
hf_ehr/tokenizers/create_cookbook_k.py
hf_ehr/tokenizers/create_desc.py
hf_ehr/tokenizers/utils.py
hf_ehr/trainer/loaders.py
hf_ehr/trainer/samplers.py
hf_ehr-0.1.4.dist-info/LICENSE
hf_ehr-0.1.4.dist-info/METADATA
hf_ehr-0.1.4.dist-info/WHEEL
hf_ehr-0.1.4.dist-info/top_level.txt
hf_ehr-0.1.4.dist-info/RECORD
