Metadata-Version: 2.2
Name: hf_ehr
Version: 0.1.4
Summary: Code for Context Clues paper
Author: Michael Wornow
Project-URL: Homepage, https://github.com/som-shahlab/long_context_clues/
Requires-Python: >=3.10
License-File: LICENSE
Requires-Dist: polars==1.1
Requires-Dist: transformers==4.48.2
Requires-Dist: trl==0.10.1
Requires-Dist: datasets==2.14.5
Requires-Dist: pandas==2.2
Requires-Dist: tensorboard==2.14.1
Requires-Dist: lightning==2.5.0
Requires-Dist: numpy==1.26.0
Requires-Dist: pytorch-nlp==0.5.0
Requires-Dist: wandb==0.15.11
Requires-Dist: loguru==0.7.2
Requires-Dist: omegaconf==2.3.0
Requires-Dist: jaxtyping==0.2.22
Requires-Dist: mlflow==2.11.1
Requires-Dist: seaborn==0.13.2
Requires-Dist: matplotlib==3.9.2
Requires-Dist: hydra-core==1.3.2
Requires-Dist: lightgbm==3.3.5
Requires-Dist: scikit-learn==1.2.2
Requires-Dist: scipy==1.10.1
Requires-Dist: tqdm==4.65.0
Requires-Dist: tabulate==0.9.0
Requires-Dist: huggingface_hub==0.26.5
Requires-Dist: meds==0.3.3
Requires-Dist: meds_reader==0.1.9
Requires-Dist: meds_etl==0.3.8
Requires-Dist: femr==0.1.16
Requires-Dist: pyyaml==6.0.1
Requires-Dist: build
Requires-Dist: twine
Requires-Dist: torch
